{
  "name": "wyn",
  "word": "identifier",
  "rules": {
    "source_file": {
      "type": "REPEAT",
      "content": {
        "type": "SYMBOL",
        "name": "_declaration"
      }
    },
    "_declaration": {
      "type": "CHOICE",
      "members": [
        {
          "type": "SYMBOL",
          "name": "def_declaration"
        },
        {
          "type": "SYMBOL",
          "name": "extern_declaration"
        },
        {
          "type": "SYMBOL",
          "name": "entry_declaration"
        },
        {
          "type": "SYMBOL",
          "name": "sig_declaration"
        },
        {
          "type": "SYMBOL",
          "name": "type_declaration"
        },
        {
          "type": "SYMBOL",
          "name": "module_declaration"
        },
        {
          "type": "SYMBOL",
          "name": "functor_declaration"
        },
        {
          "type": "SYMBOL",
          "name": "open_declaration"
        },
        {
          "type": "SYMBOL",
          "name": "import_declaration"
        }
      ]
    },
    "def_declaration": {
      "type": "SEQ",
      "members": [
        {
          "type": "CHOICE",
          "members": [
            {
              "type": "SYMBOL",
              "name": "attribute"
            },
            {
              "type": "BLANK"
            }
          ]
        },
        {
          "type": "STRING",
          "value": "def"
        },
        {
          "type": "FIELD",
          "name": "name",
          "content": {
            "type": "SYMBOL",
            "name": "identifier"
          }
        },
        {
          "type": "CHOICE",
          "members": [
            {
              "type": "SEQ",
              "members": [
                {
                  "type": "SYMBOL",
                  "name": "params"
                },
                {
                  "type": "CHOICE",
                  "members": [
                    {
                      "type": "FIELD",
                      "name": "return_type",
                      "content": {
                        "type": "SYMBOL",
                        "name": "_type"
                      }
                    },
                    {
                      "type": "BLANK"
                    }
                  ]
                }
              ]
            },
            {
              "type": "CHOICE",
              "members": [
                {
                  "type": "SEQ",
                  "members": [
                    {
                      "type": "STRING",
                      "value": ":"
                    },
                    {
                      "type": "FIELD",
                      "name": "return_type",
                      "content": {
                        "type": "SYMBOL",
                        "name": "_type"
                      }
                    }
                  ]
                },
                {
                  "type": "BLANK"
                }
              ]
            }
          ]
        },
        {
          "type": "STRING",
          "value": "="
        },
        {
          "type": "FIELD",
          "name": "body",
          "content": {
            "type": "SYMBOL",
            "name": "_expression"
          }
        }
      ]
    },
    "extern_declaration": {
      "type": "SEQ",
      "members": [
        {
          "type": "SYMBOL",
          "name": "attribute"
        },
        {
          "type": "STRING",
          "value": "def"
        },
        {
          "type": "FIELD",
          "name": "name",
          "content": {
            "type": "SYMBOL",
            "name": "identifier"
          }
        },
        {
          "type": "STRING",
          "value": ":"
        },
        {
          "type": "FIELD",
          "name": "type",
          "content": {
            "type": "SYMBOL",
            "name": "_type"
          }
        }
      ]
    },
    "entry_declaration": {
      "type": "SEQ",
      "members": [
        {
          "type": "CHOICE",
          "members": [
            {
              "type": "SYMBOL",
              "name": "attribute"
            },
            {
              "type": "BLANK"
            }
          ]
        },
        {
          "type": "STRING",
          "value": "entry"
        },
        {
          "type": "FIELD",
          "name": "name",
          "content": {
            "type": "SYMBOL",
            "name": "identifier"
          }
        },
        {
          "type": "SYMBOL",
          "name": "params"
        },
        {
          "type": "CHOICE",
          "members": [
            {
              "type": "SYMBOL",
              "name": "attribute"
            },
            {
              "type": "BLANK"
            }
          ]
        },
        {
          "type": "FIELD",
          "name": "return_type",
          "content": {
            "type": "SYMBOL",
            "name": "_type"
          }
        },
        {
          "type": "STRING",
          "value": "="
        },
        {
          "type": "FIELD",
          "name": "body",
          "content": {
            "type": "SYMBOL",
            "name": "_expression"
          }
        }
      ]
    },
    "sig_declaration": {
      "type": "SEQ",
      "members": [
        {
          "type": "STRING",
          "value": "sig"
        },
        {
          "type": "FIELD",
          "name": "name",
          "content": {
            "type": "CHOICE",
            "members": [
              {
                "type": "SYMBOL",
                "name": "identifier"
              },
              {
                "type": "SYMBOL",
                "name": "operator_name"
              }
            ]
          }
        },
        {
          "type": "STRING",
          "value": ":"
        },
        {
          "type": "FIELD",
          "name": "type",
          "content": {
            "type": "SYMBOL",
            "name": "_type"
          }
        }
      ]
    },
    "type_declaration": {
      "type": "SEQ",
      "members": [
        {
          "type": "STRING",
          "value": "type"
        },
        {
          "type": "FIELD",
          "name": "name",
          "content": {
            "type": "SYMBOL",
            "name": "identifier"
          }
        },
        {
          "type": "CHOICE",
          "members": [
            {
              "type": "SYMBOL",
              "name": "type_params"
            },
            {
              "type": "BLANK"
            }
          ]
        },
        {
          "type": "STRING",
          "value": "="
        },
        {
          "type": "FIELD",
          "name": "definition",
          "content": {
            "type": "SYMBOL",
            "name": "_type"
          }
        }
      ]
    },
    "module_declaration": {
      "type": "SEQ",
      "members": [
        {
          "type": "STRING",
          "value": "module"
        },
        {
          "type": "FIELD",
          "name": "name",
          "content": {
            "type": "SYMBOL",
            "name": "identifier"
          }
        },
        {
          "type": "STRING",
          "value": "="
        },
        {
          "type": "FIELD",
          "name": "body",
          "content": {
            "type": "SYMBOL",
            "name": "module_body"
          }
        }
      ]
    },
    "functor_declaration": {
      "type": "SEQ",
      "members": [
        {
          "type": "STRING",
          "value": "functor"
        },
        {
          "type": "FIELD",
          "name": "name",
          "content": {
            "type": "SYMBOL",
            "name": "identifier"
          }
        },
        {
          "type": "SYMBOL",
          "name": "functor_params"
        },
        {
          "type": "STRING",
          "value": "="
        },
        {
          "type": "FIELD",
          "name": "body",
          "content": {
            "type": "SYMBOL",
            "name": "module_body"
          }
        }
      ]
    },
    "functor_params": {
      "type": "SEQ",
      "members": [
        {
          "type": "STRING",
          "value": "("
        },
        {
          "type": "SEQ",
          "members": [
            {
              "type": "SYMBOL",
              "name": "functor_param"
            },
            {
              "type": "REPEAT",
              "content": {
                "type": "SEQ",
                "members": [
                  {
                    "type": "STRING",
                    "value": ","
                  },
                  {
                    "type": "SYMBOL",
                    "name": "functor_param"
                  }
                ]
              }
            },
            {
              "type": "CHOICE",
              "members": [
                {
                  "type": "STRING",
                  "value": ","
                },
                {
                  "type": "BLANK"
                }
              ]
            }
          ]
        },
        {
          "type": "STRING",
          "value": ")"
        }
      ]
    },
    "functor_param": {
      "type": "SEQ",
      "members": [
        {
          "type": "FIELD",
          "name": "name",
          "content": {
            "type": "SYMBOL",
            "name": "identifier"
          }
        },
        {
          "type": "STRING",
          "value": ":"
        },
        {
          "type": "FIELD",
          "name": "type",
          "content": {
            "type": "SYMBOL",
            "name": "_type"
          }
        }
      ]
    },
    "module_body": {
      "type": "SEQ",
      "members": [
        {
          "type": "STRING",
          "value": "{"
        },
        {
          "type": "REPEAT",
          "content": {
            "type": "SYMBOL",
            "name": "_declaration"
          }
        },
        {
          "type": "STRING",
          "value": "}"
        }
      ]
    },
    "open_declaration": {
      "type": "SEQ",
      "members": [
        {
          "type": "STRING",
          "value": "open"
        },
        {
          "type": "FIELD",
          "name": "module",
          "content": {
            "type": "SYMBOL",
            "name": "qualified_name"
          }
        }
      ]
    },
    "import_declaration": {
      "type": "SEQ",
      "members": [
        {
          "type": "STRING",
          "value": "import"
        },
        {
          "type": "FIELD",
          "name": "path",
          "content": {
            "type": "SYMBOL",
            "name": "string_literal"
          }
        }
      ]
    },
    "params": {
      "type": "SEQ",
      "members": [
        {
          "type": "STRING",
          "value": "("
        },
        {
          "type": "CHOICE",
          "members": [
            {
              "type": "SEQ",
              "members": [
                {
                  "type": "SYMBOL",
                  "name": "param"
                },
                {
                  "type": "REPEAT",
                  "content": {
                    "type": "SEQ",
                    "members": [
                      {
                        "type": "STRING",
                        "value": ","
                      },
                      {
                        "type": "SYMBOL",
                        "name": "param"
                      }
                    ]
                  }
                },
                {
                  "type": "CHOICE",
                  "members": [
                    {
                      "type": "STRING",
                      "value": ","
                    },
                    {
                      "type": "BLANK"
                    }
                  ]
                }
              ]
            },
            {
              "type": "BLANK"
            }
          ]
        },
        {
          "type": "STRING",
          "value": ")"
        }
      ]
    },
    "param": {
      "type": "SEQ",
      "members": [
        {
          "type": "CHOICE",
          "members": [
            {
              "type": "SYMBOL",
              "name": "attribute"
            },
            {
              "type": "BLANK"
            }
          ]
        },
        {
          "type": "FIELD",
          "name": "name",
          "content": {
            "type": "SYMBOL",
            "name": "identifier"
          }
        },
        {
          "type": "CHOICE",
          "members": [
            {
              "type": "SEQ",
              "members": [
                {
                  "type": "STRING",
                  "value": ":"
                },
                {
                  "type": "FIELD",
                  "name": "type",
                  "content": {
                    "type": "SYMBOL",
                    "name": "_type"
                  }
                }
              ]
            },
            {
              "type": "BLANK"
            }
          ]
        }
      ]
    },
    "type_params": {
      "type": "REPEAT1",
      "content": {
        "type": "SYMBOL",
        "name": "_type_param"
      }
    },
    "_type_param": {
      "type": "CHOICE",
      "members": [
        {
          "type": "SYMBOL",
          "name": "size_param"
        },
        {
          "type": "SYMBOL",
          "name": "type_variable"
        }
      ]
    },
    "size_param": {
      "type": "SEQ",
      "members": [
        {
          "type": "STRING",
          "value": "["
        },
        {
          "type": "SYMBOL",
          "name": "identifier"
        },
        {
          "type": "STRING",
          "value": "]"
        }
      ]
    },
    "_type": {
      "type": "CHOICE",
      "members": [
        {
          "type": "SYMBOL",
          "name": "primitive_type"
        },
        {
          "type": "SYMBOL",
          "name": "array_type"
        },
        {
          "type": "SYMBOL",
          "name": "vec_type"
        },
        {
          "type": "SYMBOL",
          "name": "mat_type"
        },
        {
          "type": "SYMBOL",
          "name": "tuple_type"
        },
        {
          "type": "SYMBOL",
          "name": "record_type"
        },
        {
          "type": "SYMBOL",
          "name": "function_type"
        },
        {
          "type": "SYMBOL",
          "name": "type_variable"
        },
        {
          "type": "SYMBOL",
          "name": "identifier"
        },
        {
          "type": "SYMBOL",
          "name": "qualified_name"
        },
        {
          "type": "SYMBOL",
          "name": "parenthesized_type"
        }
      ]
    },
    "parenthesized_type": {
      "type": "SEQ",
      "members": [
        {
          "type": "STRING",
          "value": "("
        },
        {
          "type": "SYMBOL",
          "name": "_type"
        },
        {
          "type": "STRING",
          "value": ")"
        }
      ]
    },
    "primitive_type": {
      "type": "CHOICE",
      "members": [
        {
          "type": "STRING",
          "value": "i8"
        },
        {
          "type": "STRING",
          "value": "i16"
        },
        {
          "type": "STRING",
          "value": "i32"
        },
        {
          "type": "STRING",
          "value": "i64"
        },
        {
          "type": "STRING",
          "value": "u8"
        },
        {
          "type": "STRING",
          "value": "u16"
        },
        {
          "type": "STRING",
          "value": "u32"
        },
        {
          "type": "STRING",
          "value": "u64"
        },
        {
          "type": "STRING",
          "value": "f16"
        },
        {
          "type": "STRING",
          "value": "f32"
        },
        {
          "type": "STRING",
          "value": "f64"
        },
        {
          "type": "STRING",
          "value": "bool"
        }
      ]
    },
    "array_type": {
      "type": "PREC",
      "value": 2,
      "content": {
        "type": "SEQ",
        "members": [
          {
            "type": "STRING",
            "value": "["
          },
          {
            "type": "CHOICE",
            "members": [
              {
                "type": "FIELD",
                "name": "size",
                "content": {
                  "type": "SYMBOL",
                  "name": "_expression"
                }
              },
              {
                "type": "BLANK"
              }
            ]
          },
          {
            "type": "STRING",
            "value": "]"
          },
          {
            "type": "FIELD",
            "name": "element",
            "content": {
              "type": "SYMBOL",
              "name": "_type"
            }
          }
        ]
      }
    },
    "vec_type": {
      "type": "TOKEN",
      "content": {
        "type": "PREC",
        "value": 2,
        "content": {
          "type": "PATTERN",
          "value": "vec[234](i32|u32|f16|f32|f64)"
        }
      }
    },
    "mat_type": {
      "type": "TOKEN",
      "content": {
        "type": "PREC",
        "value": 2,
        "content": {
          "type": "PATTERN",
          "value": "mat[234](x[234])?(i32|u32|f16|f32|f64)"
        }
      }
    },
    "tuple_type": {
      "type": "CHOICE",
      "members": [
        {
          "type": "SEQ",
          "members": [
            {
              "type": "STRING",
              "value": "("
            },
            {
              "type": "STRING",
              "value": ")"
            }
          ]
        },
        {
          "type": "SEQ",
          "members": [
            {
              "type": "STRING",
              "value": "("
            },
            {
              "type": "SYMBOL",
              "name": "_type"
            },
            {
              "type": "STRING",
              "value": ","
            },
            {
              "type": "CHOICE",
              "members": [
                {
                  "type": "SEQ",
                  "members": [
                    {
                      "type": "SYMBOL",
                      "name": "_type"
                    },
                    {
                      "type": "REPEAT",
                      "content": {
                        "type": "SEQ",
                        "members": [
                          {
                            "type": "STRING",
                            "value": ","
                          },
                          {
                            "type": "SYMBOL",
                            "name": "_type"
                          }
                        ]
                      }
                    },
                    {
                      "type": "CHOICE",
                      "members": [
                        {
                          "type": "STRING",
                          "value": ","
                        },
                        {
                          "type": "BLANK"
                        }
                      ]
                    }
                  ]
                },
                {
                  "type": "BLANK"
                }
              ]
            },
            {
              "type": "STRING",
              "value": ")"
            }
          ]
        }
      ]
    },
    "record_type": {
      "type": "SEQ",
      "members": [
        {
          "type": "STRING",
          "value": "{"
        },
        {
          "type": "CHOICE",
          "members": [
            {
              "type": "SEQ",
              "members": [
                {
                  "type": "SYMBOL",
                  "name": "record_field_type"
                },
                {
                  "type": "REPEAT",
                  "content": {
                    "type": "SEQ",
                    "members": [
                      {
                        "type": "STRING",
                        "value": ","
                      },
                      {
                        "type": "SYMBOL",
                        "name": "record_field_type"
                      }
                    ]
                  }
                },
                {
                  "type": "CHOICE",
                  "members": [
                    {
                      "type": "STRING",
                      "value": ","
                    },
                    {
                      "type": "BLANK"
                    }
                  ]
                }
              ]
            },
            {
              "type": "BLANK"
            }
          ]
        },
        {
          "type": "STRING",
          "value": "}"
        }
      ]
    },
    "record_field_type": {
      "type": "SEQ",
      "members": [
        {
          "type": "FIELD",
          "name": "name",
          "content": {
            "type": "SYMBOL",
            "name": "identifier"
          }
        },
        {
          "type": "STRING",
          "value": ":"
        },
        {
          "type": "FIELD",
          "name": "type",
          "content": {
            "type": "SYMBOL",
            "name": "_type"
          }
        }
      ]
    },
    "function_type": {
      "type": "PREC_RIGHT",
      "value": 0,
      "content": {
        "type": "SEQ",
        "members": [
          {
            "type": "FIELD",
            "name": "param",
            "content": {
              "type": "SYMBOL",
              "name": "_type"
            }
          },
          {
            "type": "STRING",
            "value": "->"
          },
          {
            "type": "FIELD",
            "name": "return",
            "content": {
              "type": "SYMBOL",
              "name": "_type"
            }
          }
        ]
      }
    },
    "type_variable": {
      "type": "SEQ",
      "members": [
        {
          "type": "STRING",
          "value": "'"
        },
        {
          "type": "SYMBOL",
          "name": "identifier"
        }
      ]
    },
    "_expression": {
      "type": "CHOICE",
      "members": [
        {
          "type": "SYMBOL",
          "name": "let_expression"
        },
        {
          "type": "SYMBOL",
          "name": "if_expression"
        },
        {
          "type": "SYMBOL",
          "name": "loop_expression"
        },
        {
          "type": "SYMBOL",
          "name": "match_expression"
        },
        {
          "type": "SYMBOL",
          "name": "lambda_expression"
        },
        {
          "type": "SYMBOL",
          "name": "_binary_expression"
        },
        {
          "type": "SYMBOL",
          "name": "unary_expression"
        },
        {
          "type": "SYMBOL",
          "name": "field_expression"
        },
        {
          "type": "SYMBOL",
          "name": "index_expression"
        },
        {
          "type": "SYMBOL",
          "name": "call_expression"
        },
        {
          "type": "SYMBOL",
          "name": "type_ascription"
        },
        {
          "type": "SYMBOL",
          "name": "type_coercion"
        },
        {
          "type": "SYMBOL",
          "name": "_primary_expression"
        }
      ]
    },
    "let_expression": {
      "type": "PREC_RIGHT",
      "value": 0,
      "content": {
        "type": "SEQ",
        "members": [
          {
            "type": "STRING",
            "value": "let"
          },
          {
            "type": "FIELD",
            "name": "pattern",
            "content": {
              "type": "SYMBOL",
              "name": "_pattern"
            }
          },
          {
            "type": "CHOICE",
            "members": [
              {
                "type": "SEQ",
                "members": [
                  {
                    "type": "STRING",
                    "value": ":"
                  },
                  {
                    "type": "FIELD",
                    "name": "type",
                    "content": {
                      "type": "SYMBOL",
                      "name": "_type"
                    }
                  }
                ]
              },
              {
                "type": "BLANK"
              }
            ]
          },
          {
            "type": "STRING",
            "value": "="
          },
          {
            "type": "FIELD",
            "name": "value",
            "content": {
              "type": "SYMBOL",
              "name": "_expression"
            }
          },
          {
            "type": "STRING",
            "value": "in"
          },
          {
            "type": "FIELD",
            "name": "body",
            "content": {
              "type": "SYMBOL",
              "name": "_expression"
            }
          }
        ]
      }
    },
    "if_expression": {
      "type": "PREC_RIGHT",
      "value": 0,
      "content": {
        "type": "SEQ",
        "members": [
          {
            "type": "STRING",
            "value": "if"
          },
          {
            "type": "FIELD",
            "name": "condition",
            "content": {
              "type": "SYMBOL",
              "name": "_expression"
            }
          },
          {
            "type": "STRING",
            "value": "then"
          },
          {
            "type": "FIELD",
            "name": "then",
            "content": {
              "type": "SYMBOL",
              "name": "_expression"
            }
          },
          {
            "type": "STRING",
            "value": "else"
          },
          {
            "type": "FIELD",
            "name": "else",
            "content": {
              "type": "SYMBOL",
              "name": "_expression"
            }
          }
        ]
      }
    },
    "loop_expression": {
      "type": "PREC_RIGHT",
      "value": 0,
      "content": {
        "type": "SEQ",
        "members": [
          {
            "type": "STRING",
            "value": "loop"
          },
          {
            "type": "FIELD",
            "name": "pattern",
            "content": {
              "type": "SYMBOL",
              "name": "_pattern"
            }
          },
          {
            "type": "CHOICE",
            "members": [
              {
                "type": "SEQ",
                "members": [
                  {
                    "type": "STRING",
                    "value": "="
                  },
                  {
                    "type": "FIELD",
                    "name": "init",
                    "content": {
                      "type": "SYMBOL",
                      "name": "_expression"
                    }
                  }
                ]
              },
              {
                "type": "BLANK"
              }
            ]
          },
          {
            "type": "FIELD",
            "name": "form",
            "content": {
              "type": "SYMBOL",
              "name": "_loop_form"
            }
          },
          {
            "type": "STRING",
            "value": "do"
          },
          {
            "type": "FIELD",
            "name": "body",
            "content": {
              "type": "SYMBOL",
              "name": "_expression"
            }
          }
        ]
      }
    },
    "_loop_form": {
      "type": "CHOICE",
      "members": [
        {
          "type": "SYMBOL",
          "name": "for_loop"
        },
        {
          "type": "SYMBOL",
          "name": "for_in_loop"
        },
        {
          "type": "SYMBOL",
          "name": "while_loop"
        }
      ]
    },
    "for_loop": {
      "type": "SEQ",
      "members": [
        {
          "type": "STRING",
          "value": "for"
        },
        {
          "type": "FIELD",
          "name": "var",
          "content": {
            "type": "SYMBOL",
            "name": "identifier"
          }
        },
        {
          "type": "STRING",
          "value": "<"
        },
        {
          "type": "FIELD",
          "name": "bound",
          "content": {
            "type": "SYMBOL",
            "name": "_expression"
          }
        }
      ]
    },
    "for_in_loop": {
      "type": "SEQ",
      "members": [
        {
          "type": "STRING",
          "value": "for"
        },
        {
          "type": "FIELD",
          "name": "pattern",
          "content": {
            "type": "SYMBOL",
            "name": "_pattern"
          }
        },
        {
          "type": "STRING",
          "value": "in"
        },
        {
          "type": "FIELD",
          "name": "iterable",
          "content": {
            "type": "SYMBOL",
            "name": "_expression"
          }
        }
      ]
    },
    "while_loop": {
      "type": "SEQ",
      "members": [
        {
          "type": "STRING",
          "value": "while"
        },
        {
          "type": "FIELD",
          "name": "condition",
          "content": {
            "type": "SYMBOL",
            "name": "_expression"
          }
        }
      ]
    },
    "match_expression": {
      "type": "PREC_RIGHT",
      "value": 0,
      "content": {
        "type": "SEQ",
        "members": [
          {
            "type": "STRING",
            "value": "match"
          },
          {
            "type": "FIELD",
            "name": "value",
            "content": {
              "type": "SYMBOL",
              "name": "_expression"
            }
          },
          {
            "type": "REPEAT1",
            "content": {
              "type": "SYMBOL",
              "name": "case_clause"
            }
          }
        ]
      }
    },
    "case_clause": {
      "type": "SEQ",
      "members": [
        {
          "type": "STRING",
          "value": "case"
        },
        {
          "type": "FIELD",
          "name": "pattern",
          "content": {
            "type": "SYMBOL",
            "name": "_pattern"
          }
        },
        {
          "type": "STRING",
          "value": "->"
        },
        {
          "type": "FIELD",
          "name": "body",
          "content": {
            "type": "SYMBOL",
            "name": "_expression"
          }
        }
      ]
    },
    "lambda_expression": {
      "type": "PREC_RIGHT",
      "value": 0,
      "content": {
        "type": "SEQ",
        "members": [
          {
            "type": "CHOICE",
            "members": [
              {
                "type": "SEQ",
                "members": [
                  {
                    "type": "STRING",
                    "value": "|"
                  },
                  {
                    "type": "CHOICE",
                    "members": [
                      {
                        "type": "SEQ",
                        "members": [
                          {
                            "type": "SYMBOL",
                            "name": "_pattern"
                          },
                          {
                            "type": "REPEAT",
                            "content": {
                              "type": "SEQ",
                              "members": [
                                {
                                  "type": "STRING",
                                  "value": ","
                                },
                                {
                                  "type": "SYMBOL",
                                  "name": "_pattern"
                                }
                              ]
                            }
                          },
                          {
                            "type": "CHOICE",
                            "members": [
                              {
                                "type": "STRING",
                                "value": ","
                              },
                              {
                                "type": "BLANK"
                              }
                            ]
                          }
                        ]
                      },
                      {
                        "type": "BLANK"
                      }
                    ]
                  },
                  {
                    "type": "STRING",
                    "value": "|"
                  }
                ]
              },
              {
                "type": "STRING",
                "value": "||"
              }
            ]
          },
          {
            "type": "FIELD",
            "name": "body",
            "content": {
              "type": "SYMBOL",
              "name": "_expression"
            }
          }
        ]
      }
    },
    "_binary_expression": {
      "type": "CHOICE",
      "members": [
        {
          "type": "PREC_LEFT",
          "value": 4,
          "content": {
            "type": "SEQ",
            "members": [
              {
                "type": "FIELD",
                "name": "left",
                "content": {
                  "type": "SYMBOL",
                  "name": "_expression"
                }
              },
              {
                "type": "FIELD",
                "name": "operator",
                "content": {
                  "type": "STRING",
                  "value": "||"
                }
              },
              {
                "type": "FIELD",
                "name": "right",
                "content": {
                  "type": "SYMBOL",
                  "name": "_expression"
                }
              }
            ]
          }
        },
        {
          "type": "PREC_LEFT",
          "value": 5,
          "content": {
            "type": "SEQ",
            "members": [
              {
                "type": "FIELD",
                "name": "left",
                "content": {
                  "type": "SYMBOL",
                  "name": "_expression"
                }
              },
              {
                "type": "FIELD",
                "name": "operator",
                "content": {
                  "type": "STRING",
                  "value": "&&"
                }
              },
              {
                "type": "FIELD",
                "name": "right",
                "content": {
                  "type": "SYMBOL",
                  "name": "_expression"
                }
              }
            ]
          }
        },
        {
          "type": "PREC_LEFT",
          "value": 6,
          "content": {
            "type": "SEQ",
            "members": [
              {
                "type": "FIELD",
                "name": "left",
                "content": {
                  "type": "SYMBOL",
                  "name": "_expression"
                }
              },
              {
                "type": "FIELD",
                "name": "operator",
                "content": {
                  "type": "CHOICE",
                  "members": [
                    {
                      "type": "STRING",
                      "value": "=="
                    },
                    {
                      "type": "STRING",
                      "value": "!="
                    },
                    {
                      "type": "STRING",
                      "value": "<"
                    },
                    {
                      "type": "STRING",
                      "value": "<="
                    },
                    {
                      "type": "STRING",
                      "value": ">"
                    },
                    {
                      "type": "STRING",
                      "value": ">="
                    }
                  ]
                }
              },
              {
                "type": "FIELD",
                "name": "right",
                "content": {
                  "type": "SYMBOL",
                  "name": "_expression"
                }
              }
            ]
          }
        },
        {
          "type": "PREC_LEFT",
          "value": 7,
          "content": {
            "type": "SEQ",
            "members": [
              {
                "type": "FIELD",
                "name": "left",
                "content": {
                  "type": "SYMBOL",
                  "name": "_expression"
                }
              },
              {
                "type": "FIELD",
                "name": "operator",
                "content": {
                  "type": "CHOICE",
                  "members": [
                    {
                      "type": "STRING",
                      "value": "&"
                    },
                    {
                      "type": "STRING",
                      "value": "^"
                    }
                  ]
                }
              },
              {
                "type": "FIELD",
                "name": "right",
                "content": {
                  "type": "SYMBOL",
                  "name": "_expression"
                }
              }
            ]
          }
        },
        {
          "type": "PREC_LEFT",
          "value": 8,
          "content": {
            "type": "SEQ",
            "members": [
              {
                "type": "FIELD",
                "name": "left",
                "content": {
                  "type": "SYMBOL",
                  "name": "_expression"
                }
              },
              {
                "type": "FIELD",
                "name": "operator",
                "content": {
                  "type": "CHOICE",
                  "members": [
                    {
                      "type": "STRING",
                      "value": "<<"
                    },
                    {
                      "type": "STRING",
                      "value": ">>"
                    },
                    {
                      "type": "STRING",
                      "value": ">>>"
                    }
                  ]
                }
              },
              {
                "type": "FIELD",
                "name": "right",
                "content": {
                  "type": "SYMBOL",
                  "name": "_expression"
                }
              }
            ]
          }
        },
        {
          "type": "PREC_LEFT",
          "value": 9,
          "content": {
            "type": "SEQ",
            "members": [
              {
                "type": "FIELD",
                "name": "left",
                "content": {
                  "type": "SYMBOL",
                  "name": "_expression"
                }
              },
              {
                "type": "FIELD",
                "name": "operator",
                "content": {
                  "type": "CHOICE",
                  "members": [
                    {
                      "type": "STRING",
                      "value": "+"
                    },
                    {
                      "type": "STRING",
                      "value": "-"
                    }
                  ]
                }
              },
              {
                "type": "FIELD",
                "name": "right",
                "content": {
                  "type": "SYMBOL",
                  "name": "_expression"
                }
              }
            ]
          }
        },
        {
          "type": "PREC_LEFT",
          "value": 10,
          "content": {
            "type": "SEQ",
            "members": [
              {
                "type": "FIELD",
                "name": "left",
                "content": {
                  "type": "SYMBOL",
                  "name": "_expression"
                }
              },
              {
                "type": "FIELD",
                "name": "operator",
                "content": {
                  "type": "CHOICE",
                  "members": [
                    {
                      "type": "STRING",
                      "value": "*"
                    },
                    {
                      "type": "STRING",
                      "value": "/"
                    },
                    {
                      "type": "STRING",
                      "value": "%"
                    },
                    {
                      "type": "STRING",
                      "value": "//"
                    },
                    {
                      "type": "STRING",
                      "value": "%%"
                    }
                  ]
                }
              },
              {
                "type": "FIELD",
                "name": "right",
                "content": {
                  "type": "SYMBOL",
                  "name": "_expression"
                }
              }
            ]
          }
        },
        {
          "type": "PREC_LEFT",
          "value": 11,
          "content": {
            "type": "SEQ",
            "members": [
              {
                "type": "FIELD",
                "name": "left",
                "content": {
                  "type": "SYMBOL",
                  "name": "_expression"
                }
              },
              {
                "type": "FIELD",
                "name": "operator",
                "content": {
                  "type": "STRING",
                  "value": "|>"
                }
              },
              {
                "type": "FIELD",
                "name": "right",
                "content": {
                  "type": "SYMBOL",
                  "name": "_expression"
                }
              }
            ]
          }
        },
        {
          "type": "PREC_RIGHT",
          "value": 12,
          "content": {
            "type": "SEQ",
            "members": [
              {
                "type": "FIELD",
                "name": "left",
                "content": {
                  "type": "SYMBOL",
                  "name": "_expression"
                }
              },
              {
                "type": "FIELD",
                "name": "operator",
                "content": {
                  "type": "STRING",
                  "value": "**"
                }
              },
              {
                "type": "FIELD",
                "name": "right",
                "content": {
                  "type": "SYMBOL",
                  "name": "_expression"
                }
              }
            ]
          }
        },
        {
          "type": "PREC_LEFT",
          "value": 6,
          "content": {
            "type": "SEQ",
            "members": [
              {
                "type": "FIELD",
                "name": "left",
                "content": {
                  "type": "SYMBOL",
                  "name": "_expression"
                }
              },
              {
                "type": "FIELD",
                "name": "operator",
                "content": {
                  "type": "CHOICE",
                  "members": [
                    {
                      "type": "STRING",
                      "value": ".."
                    },
                    {
                      "type": "STRING",
                      "value": "..<"
                    },
                    {
                      "type": "STRING",
                      "value": "..>"
                    },
                    {
                      "type": "STRING",
                      "value": "..."
                    }
                  ]
                }
              },
              {
                "type": "FIELD",
                "name": "right",
                "content": {
                  "type": "SYMBOL",
                  "name": "_expression"
                }
              }
            ]
          }
        }
      ]
    },
    "unary_expression": {
      "type": "PREC",
      "value": 13,
      "content": {
        "type": "CHOICE",
        "members": [
          {
            "type": "SEQ",
            "members": [
              {
                "type": "STRING",
                "value": "-"
              },
              {
                "type": "FIELD",
                "name": "operand",
                "content": {
                  "type": "SYMBOL",
                  "name": "_expression"
                }
              }
            ]
          },
          {
            "type": "SEQ",
            "members": [
              {
                "type": "STRING",
                "value": "!"
              },
              {
                "type": "FIELD",
                "name": "operand",
                "content": {
                  "type": "SYMBOL",
                  "name": "_expression"
                }
              }
            ]
          }
        ]
      }
    },
    "field_expression": {
      "type": "PREC_LEFT",
      "value": 14,
      "content": {
        "type": "SEQ",
        "members": [
          {
            "type": "FIELD",
            "name": "object",
            "content": {
              "type": "SYMBOL",
              "name": "_expression"
            }
          },
          {
            "type": "STRING",
            "value": "."
          },
          {
            "type": "FIELD",
            "name": "field",
            "content": {
              "type": "CHOICE",
              "members": [
                {
                  "type": "SYMBOL",
                  "name": "identifier"
                },
                {
                  "type": "SYMBOL",
                  "name": "integer_literal"
                }
              ]
            }
          }
        ]
      }
    },
    "index_expression": {
      "type": "PREC_LEFT",
      "value": 14,
      "content": {
        "type": "SEQ",
        "members": [
          {
            "type": "FIELD",
            "name": "object",
            "content": {
              "type": "SYMBOL",
              "name": "_expression"
            }
          },
          {
            "type": "STRING",
            "value": "["
          },
          {
            "type": "CHOICE",
            "members": [
              {
                "type": "SEQ",
                "members": [
                  {
                    "type": "CHOICE",
                    "members": [
                      {
                        "type": "FIELD",
                        "name": "start",
                        "content": {
                          "type": "SYMBOL",
                          "name": "_expression"
                        }
                      },
                      {
                        "type": "BLANK"
                      }
                    ]
                  },
                  {
                    "type": "STRING",
                    "value": ".."
                  },
                  {
                    "type": "CHOICE",
                    "members": [
                      {
                        "type": "FIELD",
                        "name": "end",
                        "content": {
                          "type": "SYMBOL",
                          "name": "_expression"
                        }
                      },
                      {
                        "type": "BLANK"
                      }
                    ]
                  }
                ]
              },
              {
                "type": "SEQ",
                "members": [
                  {
                    "type": "SYMBOL",
                    "name": "_expression"
                  },
                  {
                    "type": "REPEAT",
                    "content": {
                      "type": "SEQ",
                      "members": [
                        {
                          "type": "STRING",
                          "value": ","
                        },
                        {
                          "type": "SYMBOL",
                          "name": "_expression"
                        }
                      ]
                    }
                  },
                  {
                    "type": "CHOICE",
                    "members": [
                      {
                        "type": "STRING",
                        "value": ","
                      },
                      {
                        "type": "BLANK"
                      }
                    ]
                  }
                ]
              }
            ]
          },
          {
            "type": "STRING",
            "value": "]"
          }
        ]
      }
    },
    "call_expression": {
      "type": "PREC_LEFT",
      "value": 15,
      "content": {
        "type": "SEQ",
        "members": [
          {
            "type": "FIELD",
            "name": "function",
            "content": {
              "type": "SYMBOL",
              "name": "_expression"
            }
          },
          {
            "type": "STRING",
            "value": "("
          },
          {
            "type": "CHOICE",
            "members": [
              {
                "type": "SEQ",
                "members": [
                  {
                    "type": "SYMBOL",
                    "name": "_expression"
                  },
                  {
                    "type": "REPEAT",
                    "content": {
                      "type": "SEQ",
                      "members": [
                        {
                          "type": "STRING",
                          "value": ","
                        },
                        {
                          "type": "SYMBOL",
                          "name": "_expression"
                        }
                      ]
                    }
                  },
                  {
                    "type": "CHOICE",
                    "members": [
                      {
                        "type": "STRING",
                        "value": ","
                      },
                      {
                        "type": "BLANK"
                      }
                    ]
                  }
                ]
              },
              {
                "type": "BLANK"
              }
            ]
          },
          {
            "type": "STRING",
            "value": ")"
          }
        ]
      }
    },
    "type_ascription": {
      "type": "PREC_LEFT",
      "value": 2,
      "content": {
        "type": "SEQ",
        "members": [
          {
            "type": "FIELD",
            "name": "expression",
            "content": {
              "type": "SYMBOL",
              "name": "_expression"
            }
          },
          {
            "type": "STRING",
            "value": ":"
          },
          {
            "type": "FIELD",
            "name": "type",
            "content": {
              "type": "SYMBOL",
              "name": "_type"
            }
          }
        ]
      }
    },
    "type_coercion": {
      "type": "PREC_LEFT",
      "value": 3,
      "content": {
        "type": "SEQ",
        "members": [
          {
            "type": "FIELD",
            "name": "expression",
            "content": {
              "type": "SYMBOL",
              "name": "_expression"
            }
          },
          {
            "type": "STRING",
            "value": ":>"
          },
          {
            "type": "FIELD",
            "name": "type",
            "content": {
              "type": "SYMBOL",
              "name": "_type"
            }
          }
        ]
      }
    },
    "_primary_expression": {
      "type": "CHOICE",
      "members": [
        {
          "type": "SYMBOL",
          "name": "identifier"
        },
        {
          "type": "SYMBOL",
          "name": "qualified_name"
        },
        {
          "type": "SYMBOL",
          "name": "_literal"
        },
        {
          "type": "SYMBOL",
          "name": "array_literal"
        },
        {
          "type": "SYMBOL",
          "name": "vec_literal"
        },
        {
          "type": "SYMBOL",
          "name": "tuple_expression"
        },
        {
          "type": "SYMBOL",
          "name": "record_expression"
        },
        {
          "type": "SYMBOL",
          "name": "type_hole"
        },
        {
          "type": "SYMBOL",
          "name": "curry_expression"
        },
        {
          "type": "SYMBOL",
          "name": "parenthesized_expression"
        }
      ]
    },
    "parenthesized_expression": {
      "type": "SEQ",
      "members": [
        {
          "type": "STRING",
          "value": "("
        },
        {
          "type": "SYMBOL",
          "name": "_expression"
        },
        {
          "type": "STRING",
          "value": ")"
        }
      ]
    },
    "array_literal": {
      "type": "SEQ",
      "members": [
        {
          "type": "STRING",
          "value": "["
        },
        {
          "type": "CHOICE",
          "members": [
            {
              "type": "SEQ",
              "members": [
                {
                  "type": "SYMBOL",
                  "name": "_expression"
                },
                {
                  "type": "REPEAT",
                  "content": {
                    "type": "SEQ",
                    "members": [
                      {
                        "type": "STRING",
                        "value": ","
                      },
                      {
                        "type": "SYMBOL",
                        "name": "_expression"
                      }
                    ]
                  }
                },
                {
                  "type": "CHOICE",
                  "members": [
                    {
                      "type": "STRING",
                      "value": ","
                    },
                    {
                      "type": "BLANK"
                    }
                  ]
                }
              ]
            },
            {
              "type": "BLANK"
            }
          ]
        },
        {
          "type": "STRING",
          "value": "]"
        }
      ]
    },
    "vec_literal": {
      "type": "SEQ",
      "members": [
        {
          "type": "STRING",
          "value": "@["
        },
        {
          "type": "CHOICE",
          "members": [
            {
              "type": "SEQ",
              "members": [
                {
                  "type": "SYMBOL",
                  "name": "_expression"
                },
                {
                  "type": "REPEAT",
                  "content": {
                    "type": "SEQ",
                    "members": [
                      {
                        "type": "STRING",
                        "value": ","
                      },
                      {
                        "type": "SYMBOL",
                        "name": "_expression"
                      }
                    ]
                  }
                },
                {
                  "type": "CHOICE",
                  "members": [
                    {
                      "type": "STRING",
                      "value": ","
                    },
                    {
                      "type": "BLANK"
                    }
                  ]
                }
              ]
            },
            {
              "type": "BLANK"
            }
          ]
        },
        {
          "type": "STRING",
          "value": "]"
        }
      ]
    },
    "tuple_expression": {
      "type": "SEQ",
      "members": [
        {
          "type": "STRING",
          "value": "("
        },
        {
          "type": "SYMBOL",
          "name": "_expression"
        },
        {
          "type": "STRING",
          "value": ","
        },
        {
          "type": "SEQ",
          "members": [
            {
              "type": "SYMBOL",
              "name": "_expression"
            },
            {
              "type": "REPEAT",
              "content": {
                "type": "SEQ",
                "members": [
                  {
                    "type": "STRING",
                    "value": ","
                  },
                  {
                    "type": "SYMBOL",
                    "name": "_expression"
                  }
                ]
              }
            },
            {
              "type": "CHOICE",
              "members": [
                {
                  "type": "STRING",
                  "value": ","
                },
                {
                  "type": "BLANK"
                }
              ]
            }
          ]
        },
        {
          "type": "STRING",
          "value": ")"
        }
      ]
    },
    "record_expression": {
      "type": "SEQ",
      "members": [
        {
          "type": "STRING",
          "value": "{"
        },
        {
          "type": "CHOICE",
          "members": [
            {
              "type": "SEQ",
              "members": [
                {
                  "type": "SYMBOL",
                  "name": "record_field"
                },
                {
                  "type": "REPEAT",
                  "content": {
                    "type": "SEQ",
                    "members": [
                      {
                        "type": "STRING",
                        "value": ","
                      },
                      {
                        "type": "SYMBOL",
                        "name": "record_field"
                      }
                    ]
                  }
                },
                {
                  "type": "CHOICE",
                  "members": [
                    {
                      "type": "STRING",
                      "value": ","
                    },
                    {
                      "type": "BLANK"
                    }
                  ]
                }
              ]
            },
            {
              "type": "BLANK"
            }
          ]
        },
        {
          "type": "STRING",
          "value": "}"
        }
      ]
    },
    "record_field": {
      "type": "CHOICE",
      "members": [
        {
          "type": "SEQ",
          "members": [
            {
              "type": "FIELD",
              "name": "name",
              "content": {
                "type": "SYMBOL",
                "name": "identifier"
              }
            },
            {
              "type": "STRING",
              "value": "="
            },
            {
              "type": "FIELD",
              "name": "value",
              "content": {
                "type": "SYMBOL",
                "name": "_expression"
              }
            }
          ]
        },
        {
          "type": "SYMBOL",
          "name": "identifier"
        }
      ]
    },
    "curry_expression": {
      "type": "SEQ",
      "members": [
        {
          "type": "STRING",
          "value": "$"
        },
        {
          "type": "FIELD",
          "name": "function",
          "content": {
            "type": "SYMBOL",
            "name": "_expression"
          }
        },
        {
          "type": "STRING",
          "value": "("
        },
        {
          "type": "CHOICE",
          "members": [
            {
              "type": "SEQ",
              "members": [
                {
                  "type": "CHOICE",
                  "members": [
                    {
                      "type": "SYMBOL",
                      "name": "_expression"
                    },
                    {
                      "type": "STRING",
                      "value": "_"
                    }
                  ]
                },
                {
                  "type": "REPEAT",
                  "content": {
                    "type": "SEQ",
                    "members": [
                      {
                        "type": "STRING",
                        "value": ","
                      },
                      {
                        "type": "CHOICE",
                        "members": [
                          {
                            "type": "SYMBOL",
                            "name": "_expression"
                          },
                          {
                            "type": "STRING",
                            "value": "_"
                          }
                        ]
                      }
                    ]
                  }
                },
                {
                  "type": "CHOICE",
                  "members": [
                    {
                      "type": "STRING",
                      "value": ","
                    },
                    {
                      "type": "BLANK"
                    }
                  ]
                }
              ]
            },
            {
              "type": "BLANK"
            }
          ]
        },
        {
          "type": "STRING",
          "value": ")"
        }
      ]
    },
    "type_hole": {
      "type": "STRING",
      "value": "???"
    },
    "_pattern": {
      "type": "CHOICE",
      "members": [
        {
          "type": "SYMBOL",
          "name": "identifier"
        },
        {
          "type": "SYMBOL",
          "name": "wildcard"
        },
        {
          "type": "SYMBOL",
          "name": "_literal"
        },
        {
          "type": "SYMBOL",
          "name": "tuple_pattern"
        },
        {
          "type": "SYMBOL",
          "name": "record_pattern"
        },
        {
          "type": "SYMBOL",
          "name": "parenthesized_pattern"
        }
      ]
    },
    "parenthesized_pattern": {
      "type": "SEQ",
      "members": [
        {
          "type": "STRING",
          "value": "("
        },
        {
          "type": "SYMBOL",
          "name": "_pattern"
        },
        {
          "type": "STRING",
          "value": ")"
        }
      ]
    },
    "wildcard": {
      "type": "STRING",
      "value": "_"
    },
    "tuple_pattern": {
      "type": "SEQ",
      "members": [
        {
          "type": "STRING",
          "value": "("
        },
        {
          "type": "SYMBOL",
          "name": "_pattern"
        },
        {
          "type": "STRING",
          "value": ","
        },
        {
          "type": "SEQ",
          "members": [
            {
              "type": "SYMBOL",
              "name": "_pattern"
            },
            {
              "type": "REPEAT",
              "content": {
                "type": "SEQ",
                "members": [
                  {
                    "type": "STRING",
                    "value": ","
                  },
                  {
                    "type": "SYMBOL",
                    "name": "_pattern"
                  }
                ]
              }
            },
            {
              "type": "CHOICE",
              "members": [
                {
                  "type": "STRING",
                  "value": ","
                },
                {
                  "type": "BLANK"
                }
              ]
            }
          ]
        },
        {
          "type": "STRING",
          "value": ")"
        }
      ]
    },
    "record_pattern": {
      "type": "SEQ",
      "members": [
        {
          "type": "STRING",
          "value": "{"
        },
        {
          "type": "CHOICE",
          "members": [
            {
              "type": "SEQ",
              "members": [
                {
                  "type": "SYMBOL",
                  "name": "record_field_pattern"
                },
                {
                  "type": "REPEAT",
                  "content": {
                    "type": "SEQ",
                    "members": [
                      {
                        "type": "STRING",
                        "value": ","
                      },
                      {
                        "type": "SYMBOL",
                        "name": "record_field_pattern"
                      }
                    ]
                  }
                },
                {
                  "type": "CHOICE",
                  "members": [
                    {
                      "type": "STRING",
                      "value": ","
                    },
                    {
                      "type": "BLANK"
                    }
                  ]
                }
              ]
            },
            {
              "type": "BLANK"
            }
          ]
        },
        {
          "type": "STRING",
          "value": "}"
        }
      ]
    },
    "record_field_pattern": {
      "type": "SEQ",
      "members": [
        {
          "type": "FIELD",
          "name": "name",
          "content": {
            "type": "SYMBOL",
            "name": "identifier"
          }
        },
        {
          "type": "CHOICE",
          "members": [
            {
              "type": "SEQ",
              "members": [
                {
                  "type": "STRING",
                  "value": "="
                },
                {
                  "type": "FIELD",
                  "name": "pattern",
                  "content": {
                    "type": "SYMBOL",
                    "name": "_pattern"
                  }
                }
              ]
            },
            {
              "type": "BLANK"
            }
          ]
        }
      ]
    },
    "attribute": {
      "type": "SEQ",
      "members": [
        {
          "type": "STRING",
          "value": "#["
        },
        {
          "type": "SEQ",
          "members": [
            {
              "type": "SYMBOL",
              "name": "attribute_item"
            },
            {
              "type": "REPEAT",
              "content": {
                "type": "SEQ",
                "members": [
                  {
                    "type": "STRING",
                    "value": ","
                  },
                  {
                    "type": "SYMBOL",
                    "name": "attribute_item"
                  }
                ]
              }
            },
            {
              "type": "CHOICE",
              "members": [
                {
                  "type": "STRING",
                  "value": ","
                },
                {
                  "type": "BLANK"
                }
              ]
            }
          ]
        },
        {
          "type": "STRING",
          "value": "]"
        }
      ]
    },
    "attribute_item": {
      "type": "SEQ",
      "members": [
        {
          "type": "SYMBOL",
          "name": "identifier"
        },
        {
          "type": "CHOICE",
          "members": [
            {
              "type": "SEQ",
              "members": [
                {
                  "type": "STRING",
                  "value": "("
                },
                {
                  "type": "CHOICE",
                  "members": [
                    {
                      "type": "SEQ",
                      "members": [
                        {
                          "type": "SYMBOL",
                          "name": "attribute_arg"
                        },
                        {
                          "type": "REPEAT",
                          "content": {
                            "type": "SEQ",
                            "members": [
                              {
                                "type": "STRING",
                                "value": ","
                              },
                              {
                                "type": "SYMBOL",
                                "name": "attribute_arg"
                              }
                            ]
                          }
                        },
                        {
                          "type": "CHOICE",
                          "members": [
                            {
                              "type": "STRING",
                              "value": ","
                            },
                            {
                              "type": "BLANK"
                            }
                          ]
                        }
                      ]
                    },
                    {
                      "type": "BLANK"
                    }
                  ]
                },
                {
                  "type": "STRING",
                  "value": ")"
                }
              ]
            },
            {
              "type": "BLANK"
            }
          ]
        }
      ]
    },
    "attribute_arg": {
      "type": "CHOICE",
      "members": [
        {
          "type": "SEQ",
          "members": [
            {
              "type": "FIELD",
              "name": "key",
              "content": {
                "type": "SYMBOL",
                "name": "identifier"
              }
            },
            {
              "type": "STRING",
              "value": "="
            },
            {
              "type": "FIELD",
              "name": "value",
              "content": {
                "type": "CHOICE",
                "members": [
                  {
                    "type": "SYMBOL",
                    "name": "integer_literal"
                  },
                  {
                    "type": "SYMBOL",
                    "name": "identifier"
                  }
                ]
              }
            }
          ]
        },
        {
          "type": "SYMBOL",
          "name": "integer_literal"
        },
        {
          "type": "SYMBOL",
          "name": "identifier"
        }
      ]
    },
    "_literal": {
      "type": "CHOICE",
      "members": [
        {
          "type": "SYMBOL",
          "name": "integer_literal"
        },
        {
          "type": "SYMBOL",
          "name": "float_literal"
        },
        {
          "type": "SYMBOL",
          "name": "char_literal"
        },
        {
          "type": "SYMBOL",
          "name": "string_literal"
        },
        {
          "type": "SYMBOL",
          "name": "boolean_literal"
        }
      ]
    },
    "integer_literal": {
      "type": "TOKEN",
      "content": {
        "type": "SEQ",
        "members": [
          {
            "type": "CHOICE",
            "members": [
              {
                "type": "PATTERN",
                "value": "[0-9][0-9_]*"
              },
              {
                "type": "PATTERN",
                "value": "0[xX][0-9a-fA-F_]+"
              },
              {
                "type": "PATTERN",
                "value": "0[bB][01_]+"
              }
            ]
          },
          {
            "type": "CHOICE",
            "members": [
              {
                "type": "PATTERN",
                "value": "[iu](8|16|32|64)"
              },
              {
                "type": "BLANK"
              }
            ]
          }
        ]
      }
    },
    "float_literal": {
      "type": "TOKEN",
      "content": {
        "type": "SEQ",
        "members": [
          {
            "type": "CHOICE",
            "members": [
              {
                "type": "PATTERN",
                "value": "[0-9][0-9_]*\\.[0-9][0-9_]*"
              },
              {
                "type": "PATTERN",
                "value": "[0-9][0-9_]*[eE][+-]?[0-9]+"
              },
              {
                "type": "PATTERN",
                "value": "[0-9][0-9_]*\\.[0-9][0-9_]*[eE][+-]?[0-9]+"
              }
            ]
          },
          {
            "type": "CHOICE",
            "members": [
              {
                "type": "PATTERN",
                "value": "f(16|32|64)"
              },
              {
                "type": "BLANK"
              }
            ]
          }
        ]
      }
    },
    "char_literal": {
      "type": "PATTERN",
      "value": "'[^'\\\\]'"
    },
    "string_literal": {
      "type": "PATTERN",
      "value": "\"[^\"]*\""
    },
    "boolean_literal": {
      "type": "CHOICE",
      "members": [
        {
          "type": "STRING",
          "value": "true"
        },
        {
          "type": "STRING",
          "value": "false"
        }
      ]
    },
    "identifier": {
      "type": "PATTERN",
      "value": "[a-zA-Z_][a-zA-Z0-9_']*"
    },
    "qualified_name": {
      "type": "PREC_LEFT",
      "value": 1,
      "content": {
        "type": "SEQ",
        "members": [
          {
            "type": "SYMBOL",
            "name": "identifier"
          },
          {
            "type": "REPEAT1",
            "content": {
              "type": "SEQ",
              "members": [
                {
                  "type": "STRING",
                  "value": "."
                },
                {
                  "type": "SYMBOL",
                  "name": "identifier"
                }
              ]
            }
          }
        ]
      }
    },
    "operator_name": {
      "type": "SEQ",
      "members": [
        {
          "type": "STRING",
          "value": "("
        },
        {
          "type": "SYMBOL",
          "name": "_operator"
        },
        {
          "type": "STRING",
          "value": ")"
        }
      ]
    },
    "_operator": {
      "type": "CHOICE",
      "members": [
        {
          "type": "STRING",
          "value": "+"
        },
        {
          "type": "STRING",
          "value": "-"
        },
        {
          "type": "STRING",
          "value": "*"
        },
        {
          "type": "STRING",
          "value": "/"
        },
        {
          "type": "STRING",
          "value": "%"
        },
        {
          "type": "STRING",
          "value": "**"
        },
        {
          "type": "STRING",
          "value": "//"
        },
        {
          "type": "STRING",
          "value": "%%"
        },
        {
          "type": "STRING",
          "value": "=="
        },
        {
          "type": "STRING",
          "value": "!="
        },
        {
          "type": "STRING",
          "value": "<"
        },
        {
          "type": "STRING",
          "value": "<="
        },
        {
          "type": "STRING",
          "value": ">"
        },
        {
          "type": "STRING",
          "value": ">="
        },
        {
          "type": "STRING",
          "value": "&&"
        },
        {
          "type": "STRING",
          "value": "||"
        },
        {
          "type": "STRING",
          "value": "!"
        },
        {
          "type": "STRING",
          "value": "&"
        },
        {
          "type": "STRING",
          "value": "^"
        },
        {
          "type": "STRING",
          "value": "<<"
        },
        {
          "type": "STRING",
          "value": ">>"
        },
        {
          "type": "STRING",
          "value": ">>>"
        },
        {
          "type": "STRING",
          "value": "|>"
        }
      ]
    },
    "comment": {
      "type": "TOKEN",
      "content": {
        "type": "SEQ",
        "members": [
          {
            "type": "STRING",
            "value": "--"
          },
          {
            "type": "PATTERN",
            "value": ".*"
          }
        ]
      }
    }
  },
  "extras": [
    {
      "type": "PATTERN",
      "value": "\\s"
    },
    {
      "type": "SYMBOL",
      "name": "comment"
    }
  ],
  "conflicts": [
    [
      "identifier",
      "qualified_name"
    ],
    [
      "call_expression",
      "curry_expression"
    ]
  ],
  "precedences": [],
  "externals": [],
  "inline": [],
  "supertypes": []
}
